hextech/__init__.py
hextech/classes.py
hextech/consts.py
hextech/ddragon.py
hextech/hextech.py
hextech/leaguepedia.py
hextech-1.0.12.dist-info/METADATA
hextech-1.0.12.dist-info/WHEEL
hextech-1.0.12.dist-info/top_level.txt
hextech-1.0.12.dist-info/RECORD
