Metadata-Version: 2.1
Name: hextech
Version: 1.0.12
Summary: A Python framework for accessing League of Legends esports data
Home-page: https://github.com/bujustin/hextech
Author: bujustin
Author-email: bujustin@gmail.com
License: UNKNOWN
Platform: UNKNOWN
Classifier: Programming Language :: Python :: 3
Classifier: License :: OSI Approved :: MIT License
Classifier: Operating System :: OS Independent
Requires-Dist: certifi (==2020.6.20)
Requires-Dist: chardet (==3.0.4)
Requires-Dist: idna (==2.10)
Requires-Dist: requests (==2.24.0)
Requires-Dist: urllib3 (==1.25.10)
